pororo/__init__.py
pororo/__version__.py
pororo/pororo.py
pororo/utils.py
pororo/models/__init__.py
pororo/models/caption.py
pororo/models/collocate.py
pororo/models/p2g.py
pororo/models/vad.py
pororo/models/wikipedia2vec.py
pororo/models/bart/KoBART.py
pororo/models/bart/__init__.py
pororo/models/brainOCR/__init__.py
pororo/models/brainOCR/_dataset.py
pororo/models/brainOCR/_modules.py
pororo/models/brainOCR/brainocr.py
pororo/models/brainOCR/craft.py
pororo/models/brainOCR/craft_utils.py
pororo/models/brainOCR/detection.py
pororo/models/brainOCR/imgproc.py
pororo/models/brainOCR/model.py
pororo/models/brainOCR/recognition.py
pororo/models/brainOCR/utils.py
pororo/models/brainOCR/modules/__init__.py
pororo/models/brainOCR/modules/basenet.py
pororo/models/brainOCR/modules/feature_extraction.py
pororo/models/brainOCR/modules/prediction.py
pororo/models/brainOCR/modules/sequence_modeling.py
pororo/models/brainOCR/modules/transformation.py
pororo/models/brainbert/BrainLaBERTa.py
pororo/models/brainbert/BrainRoBERTa.py
pororo/models/brainbert/CharBrainRoBERTa.py
pororo/models/brainbert/EnBERTa.py
pororo/models/brainbert/JaBERTa.py
pororo/models/brainbert/PoSLaBERTa.py
pororo/models/brainbert/PosRoBERTa.py
pororo/models/brainbert/ZhBERTa.py
pororo/models/brainbert/__init__.py
pororo/models/brainbert/utils.py
pororo/models/brainbert/criterions/__init__.py
pororo/models/brainbert/criterions/dependency_parse.py
pororo/models/brainbert/criterions/sequence_tagging.py
pororo/models/brainbert/criterions/sequence_tagging_label.py
pororo/models/brainbert/criterions/span_prediction.py
pororo/models/brainbert/tasks/__init__.py
pororo/models/brainbert/tasks/brain_roberta_task.py
pororo/models/brainbert/tasks/dependency_parse.py
pororo/models/brainbert/tasks/sequence_tagging.py
pororo/models/brainbert/tasks/sequence_tagging_label.py
pororo/models/brainbert/tasks/span_prediction.py
pororo/models/brainsbert/BrainRoBERTa.py
pororo/models/brainsbert/__init__.py
pororo-0.4.2.dist-info/LICENSE
pororo-0.4.2.dist-info/LICENSE.3rd_party_library
pororo-0.4.2.dist-info/LICENSE.3rd_party_model
pororo-0.4.2.dist-info/METADATA
pororo-0.4.2.dist-info/WHEEL
pororo-0.4.2.dist-info/top_level.txt
pororo-0.4.2.dist-info/RECORD
